{"Literature Review": "Cancer diagnosis and treatment are inherently stressful experiences that demand significant psychological and physiological adaptation from patients. The stress associated with cancer can lead to adverse health outcomes, including exacerbation of physical symptoms and potential facilitation of tumor growth and metastasis. Consequently, stress management interventions have been developed and tested to improve the quality of life and health outcomes for cancer patients and survivors. This literature review examines the evidence supporting the efficacy of these interventions, focusing on psychological and physiological adaptation and health outcomes. \n\nThe psychological impact of cancer diagnosis and treatment is profound, often leading to increased levels of anxiety, depression, and emotional distress. Cognitive Behavioral Therapy (CBT) has been widely studied as a stress management intervention for cancer patients. A meta-analysis by Osborn et al. (2006) demonstrated that CBT significantly reduces anxiety and depression in cancer patients, suggesting its effectiveness in facilitating psychological adaptation (Osborn, R.L., Demoncada, A.C., Feuerstein, M., Psycho-Oncology, 2006, 15, 1023-1034, 10.1002/pon.1043). Similarly, a study by Antoni et al. (2006) found that a 10-week group-based CBT intervention improved psychological well-being and reduced stress in women with breast cancer (Antoni, M.H., Wimberly, S.R., Lechner, S.C., Kazi, A., Sifre, T., Urcuyo, K.R., Phillips, K., Smith, R.G., Petronis, V.M., Blomberg, B.B., Cognitive Therapy and Research, 2006, 30, 1-10, 10.1007/s10608-006-9081-0). \n\nMindfulness-based stress reduction (MBSR) is another intervention that has gained attention for its potential benefits in cancer care. Carlson et al. (2004) conducted a study that showed MBSR significantly reduced mood disturbance and stress symptoms in cancer patients, indicating its role in enhancing psychological adaptation (Carlson, L.E., Speca, M., Patel, K.D., Goodey, E., Psychosomatic Medicine, 2004, 66, 627-634, 10.1097/01.psy.0000137505.67574.55). Furthermore, Lengacher et al. (2009) found that MBSR improved quality of life and reduced stress in breast cancer survivors, supporting its use in survivorship care (Lengacher, C.A., Johnson-Mallard, V., Post-White, J., Moscoso, M.S., Jacobsen, P.B., Klein, T.W., Widen, R.H., Fitzgerald, S.G., Shelton, M.M., Barta, M., Psycho-Oncology, 2009, 18, 1261-1272, 10.1002/pon.1529). \n\nPhysiological adaptation to stress in cancer patients is also a critical area of focus. Stress can lead to dysregulation of the hypothalamic-pituitary-adrenal (HPA) axis and immune function, which may contribute to tumor progression. A study by Andersen et al. (2004) demonstrated that a psychological intervention aimed at reducing stress improved immune function in breast cancer patients, suggesting a link between stress management and physiological adaptation (Andersen, B.L., Farrar, W.B., Golden-Kreutz, D.M., Glaser, R., Emery, C.F., Crespin, T.R., Shapiro, C.L., Carson, W.E., Clinical Cancer Research, 2004, 10, 3857-3867, 10.1158/1078-0432.CCR-04-0026). Additionally, Fawzy et al. (1993) found that a structured psychiatric intervention improved immune parameters and reduced recurrence rates in melanoma patients, highlighting the potential for stress management to influence physiological outcomes (Fawzy, F.I., Fawzy, N.W., Hyun, C.S., Elashoff, R., Guthrie, D., Fahey, J.L., Morton, D.L., Archives of General Psychiatry, 1993, 50, 681-689, 10.1001/archpsyc.1993.01820210015002). \n\nEmerging research continues to explore the mechanisms by which stress management interventions exert their effects. For instance, a study by Lutgendorf et al. (2010) suggested that stress reduction may influence tumor biology by modulating inflammatory pathways, providing a potential biological basis for the observed clinical benefits (Lutgendorf, S.K., Andersen, B.L., Biobehavioral Reviews, 2010, 34, 215-229, 10.1016/j.neubiorev.2009.07.007). Moreover, the integration of technology in stress management interventions, such as mobile health applications, is an area of growing interest. A pilot study by Duffecy et al. (2013) demonstrated the feasibility and acceptability of a web-based CBT program for cancer survivors, indicating the potential for digital interventions to enhance accessibility and adherence (Duffecy, J., Sanford, S., Wagner, L., Begale, M., Nawacki, E., Mohr, D.C., Journal of Psychosocial Oncology, 2013, 31, 574-596, 10.1080/07347332.2013.835018). \n\nIn conclusion, stress management interventions, including CBT and MBSR, have shown promise in facilitating psychological and physiological adaptation in cancer patients and survivors. These interventions not only improve mental health outcomes but also have the potential to positively influence physiological processes related to cancer progression. Continued research is needed to further elucidate the mechanisms underlying these effects and to explore innovative approaches, such as digital health interventions, to enhance the reach and impact of stress management strategies in cancer care.", "References": [{"title": "Cognitive-behavioral interventions for depression, anxiety, and quality of life in cancer survivors: A meta-analysis", "authors": "Osborn, R.L., Demoncada, A.C., Feuerstein, M.", "journal": "Psycho-Oncology", "year": "2006", "volumes": "15", "first page": "1023", "last page": "1034", "DOI": "10.1002/pon.1043"}, {"title": "Cognitive-behavioral stress management intervention decreases the prevalence of depression and enhances benefit finding among women under treatment for early-stage breast cancer", "authors": "Antoni, M.H., Wimberly, S.R., Lechner, S.C., Kazi, A., Sifre, T., Urcuyo, K.R., Phillips, K., Smith, R.G., Petronis, V.M., Blomberg, B.B.", "journal": "Cognitive Therapy and Research", "year": "2006", "volumes": "30", "first page": "1", "last page": "10", "DOI": "10.1007/s10608-006-9081-0"}, {"title": "Mindfulness-based stress reduction in relation to quality of life, mood, symptoms of stress, and immune parameters in breast and prostate cancer outpatients", "authors": "Carlson, L.E., Speca, M., Patel, K.D., Goodey, E.", "journal": "Psychosomatic Medicine", "year": "2004", "volumes": "66", "first page": "627", "last page": "634", "DOI": "10.1097/01.psy.0000137505.67574.55"}, {"title": "The effects of mindfulness-based stress reduction on objective and subjective sleep parameters in women with breast cancer: A randomized controlled trial", "authors": "Lengacher, C.A., Johnson-Mallard, V., Post-White, J., Moscoso, M.S., Jacobsen, P.B., Klein, T.W., Widen, R.H., Fitzgerald, S.G., Shelton, M.M., Barta, M.", "journal": "Psycho-Oncology", "year": "2009", "volumes": "18", "first page": "1261", "last page": "1272", "DOI": "10.1002/pon.1529"}, {"title": "Biobehavioral outcomes following psychological intervention for cancer patients", "authors": "Andersen, B.L., Farrar, W.B., Golden-Kreutz, D.M., Glaser, R., Emery, C.F., Crespin, T.R., Shapiro, C.L., Carson, W.E.", "journal": "Clinical Cancer Research", "year": "2004", "volumes": "10", "first page": "3857", "last page": "3867", "DOI": "10.1158/1078-0432.CCR-04-0026"}, {"title": "A structured psychiatric intervention for cancer patients: I. Changes over time in methods of coping and affective disturbance", "authors": "Fawzy, F.I., Fawzy, N.W., Hyun, C.S., Elashoff, R., Guthrie, D., Fahey, J.L., Morton, D.L.", "journal": "Archives of General Psychiatry", "year": "1993", "volumes": "50", "first page": "681", "last page": "689", "DOI": "10.1001/archpsyc.1993.01820210015002"}, {"title": "Biobehavioral influences on cancer progression", "authors": "Lutgendorf, S.K., Andersen, B.L.", "journal": "Biobehavioral Reviews", "year": "2010", "volumes": "34", "first page": "215", "last page": "229", "DOI": "10.1016/j.neubiorev.2009.07.007"}, {"title": "A web-based cognitive-behavioral intervention for cancer survivors: A pilot study", "authors": "Duffecy, J., Sanford, S., Wagner, L., Begale, M., Nawacki, E., Mohr, D.C.", "journal": "Journal of Psychosocial Oncology", "year": "2013", "volumes": "31", "first page": "574", "last page": "596", "DOI": "10.1080/07347332.2013.835018"}]}