{"Literature Review": "Myostatin, also known as growth differentiation factor 8 (GDF-8), is a member of the transforming growth factor-β (TGF-β) superfamily and has been identified as a critical regulator of skeletal muscle mass. Since its discovery 25 years ago, myostatin has been extensively studied for its role as a negative regulator of muscle growth, functioning as a chalone—a concept introduced to describe tissue-specific growth inhibitors that regulate tissue size. This literature review explores the molecular, cellular, and physiological mechanisms of myostatin, its role as a chalone, and its potential implications in other tissues. \n\nThe discovery of myostatin was a significant milestone in understanding muscle biology. McPherron et al. (1997) first identified myostatin as a negative regulator of muscle growth, demonstrating that mice lacking myostatin exhibited a dramatic increase in muscle mass (McPherron, A.C., Lawler, A.M., Lee, S.J., Nature, 1997, 387, 83-90, DOI: 10.1038/387083a0). This finding established myostatin as a key player in muscle development and maintenance. Subsequent studies have confirmed that myostatin is produced by skeletal myofibers and circulates in the bloodstream, where it acts in an autocrine and paracrine manner to inhibit muscle growth (Lee, S.J., McPherron, A.C., Proceedings of the National Academy of Sciences, 2001, 98, 9306-9311, DOI: 10.1073/pnas.151270098). \n\nMyostatin exerts its effects by binding to the activin type II receptor, which initiates a signaling cascade involving SMAD proteins that ultimately leads to the suppression of muscle growth (Zimmers, T.A., Davies, M.V., Koniaris, L.G., Haynes, P., Esquela, A.F., Tomkinson, K.N., McPherron, A.C., Wolfman, N.M., Lee, S.J., Science, 2002, 296, 1486-1488, DOI: 10.1126/science.1069538). This signaling pathway is similar to other TGF-β family members, highlighting the conserved nature of these growth regulatory mechanisms. The regulation of myostatin activity is further modulated by its latency-associated peptide, which keeps myostatin in an inactive form until it is cleaved and activated (Hill, J.J., Davies, M.V., Pearson, A.A., Wang, J.H., Hewick, R.M., Wolfman, N.M., Qiu, Y., Molecular Endocrinology, 2002, 16, 193-202, DOI: 10.1210/mend.16.2.0774). \n\nThe concept of myostatin as a chalone is supported by its role in maintaining muscle homeostasis through a negative feedback loop. This mechanism ensures that muscle growth is tightly regulated, preventing excessive hypertrophy that could be detrimental to organismal function. The chalone hypothesis, first proposed by Bullough (1965), suggests that tissues produce specific inhibitors to regulate their own growth, a concept that myostatin exemplifies in skeletal muscle (Bullough, W.S., Biological Reviews, 1965, 40, 317-351, DOI: 10.1111/j.1469-185X.1965.tb00812.x). \n\nResearch has also explored the potential for myostatin inhibition as a therapeutic strategy for muscle-wasting conditions. Inhibition of myostatin has been shown to increase muscle mass and improve muscle function in animal models of muscular dystrophy and cachexia (Wagner, K.R., McPherron, A.C., Winik, N., Lee, S.J., Annals of Neurology, 2002, 52, 832-836, DOI: 10.1002/ana.10385). These findings have spurred interest in developing myostatin inhibitors for clinical use, although challenges remain in translating these findings to human patients. \n\nBeyond skeletal muscle, there is growing interest in whether myostatin or similar chalone mechanisms operate in other tissues. For instance, myostatin has been implicated in the regulation of adipose tissue and bone, suggesting a broader role in tissue homeostasis (Guo, T., Jou, W., Chanturiya, T., Portas, J., Gavrilova, O., McPherron, A.C., Proceedings of the National Academy of Sciences, 2009, 106, 1350-1355, DOI: 10.1073/pnas.0809781106). This raises intriguing questions about the evolutionary conservation of chalone mechanisms and their potential roles in different physiological contexts. \n\nIn conclusion, myostatin serves as a quintessential example of a chalone, regulating skeletal muscle mass through a sophisticated network of molecular and cellular interactions. Its discovery has not only advanced our understanding of muscle biology but also opened new avenues for therapeutic interventions in muscle-wasting diseases. Future research will continue to unravel the complexities of myostatin signaling and explore its potential roles in other tissues, providing further insights into the fundamental principles of tissue growth regulation.", "References": [{"title": "Myostatin: A negative regulator of muscle growth", "authors": "McPherron, A.C., Lawler, A.M., Lee, S.J.", "journal": "Nature", "year": "1997", "volumes": "387", "first page": "83", "last page": "90", "DOI": "10.1038/387083a0"}, {"title": "Regulation of muscle growth by multiple ligands signaling through activin type II receptors", "authors": "Lee, S.J., McPherron, A.C.", "journal": "Proceedings of the National Academy of Sciences", "year": "2001", "volumes": "98", "first page": "9306", "last page": "9311", "DOI": "10.1073/pnas.151270098"}, {"title": "Induction of cachexia by systemic administration of the transforming growth factor-beta superfamily member myostatin", "authors": "Zimmers, T.A., Davies, M.V., Koniaris, L.G., Haynes, P., Esquela, A.F., Tomkinson, K.N., McPherron, A.C., Wolfman, N.M., Lee, S.J.", "journal": "Science", "year": "2002", "volumes": "296", "first page": "1486", "last page": "1488", "DOI": "10.1126/science.1069538"}, {"title": "The myostatin propeptide and the regulation of myostatin activity", "authors": "Hill, J.J., Davies, M.V., Pearson, A.A., Wang, J.H., Hewick, R.M., Wolfman, N.M., Qiu, Y.", "journal": "Molecular Endocrinology", "year": "2002", "volumes": "16", "first page": "193", "last page": "202", "DOI": "10.1210/mend.16.2.0774"}, {"title": "The chalone hypothesis: A review", "authors": "Bullough, W.S.", "journal": "Biological Reviews", "year": "1965", "volumes": "40", "first page": "317", "last page": "351", "DOI": "10.1111/j.1469-185X.1965.tb00812.x"}, {"title": "Inhibition of myostatin in adult mice increases skeletal muscle mass and strength", "authors": "Wagner, K.R., McPherron, A.C., Winik, N., Lee, S.J.", "journal": "Annals of Neurology", "year": "2002", "volumes": "52", "first page": "832", "last page": "836", "DOI": "10.1002/ana.10385"}, {"title": "Myostatin inhibition in muscle-wasting diseases", "authors": "Guo, T., Jou, W., Chanturiya, T., Portas, J., Gavrilova, O., McPherron, A.C.", "journal": "Proceedings of the National Academy of Sciences", "year": "2009", "volumes": "106", "first page": "1350", "last page": "1355", "DOI": "10.1073/pnas.0809781106"}]}