{"Literature Review": "The Microbiology of Biological Soil Crusts: Unveiling the Hidden World of Microorganisms in Arid Landscapes\n\nBiological soil crusts (biocrusts) are complex communities of microorganisms that thrive on soil surfaces in arid and semi-arid regions. These communities are composed of various photosynthetic primary producers, including cyanobacteria, microalgae, and cryptogams such as lichens and mosses. The recognition of biocrusts has expanded our understanding of the microbial world in extreme environments and has opened new avenues for ecological restoration and agriculture.\n\nThe composition of biocrusts is diverse and influenced by factors such as light availability, temperature, and soil type. Studies have shown that biocrusts can harbor a wide range of microorganisms, including bacteria, archaea, fungi, and viruses (1, 2). These microorganisms play a crucial role in the biogeochemical cycles of elements such as nitrogen, phosphorus, and carbon (3, 4).\n\nOne of the key characteristics of biocrusts is their ability to alter the physical behavior of soils. For example, biocrusts can increase soil porosity, reduce soil erosion, and modify soil temperature and moisture regimes (5, 6). These changes can have significant impacts on plant growth and ecosystem function (7, 8).\n\nThe microbial communities in biocrusts are also of interest due to their potential to inform our understanding of early life on land. Studies have shown that biocrusts can harbor microorganisms that are similar to those found in ancient fossils (9). This has led to the proposal that biocrusts may have played a role in the origins of life on Earth (10).\n\nIn addition to their ecological and biogeochemical roles, biocrusts also have potential applications in agriculture and ecological restoration. For example, biocrusts can be used as a natural fertilizer and soil amendment, and can help to reduce soil erosion and improve soil health (11, 12).\n\nDespite the growing interest in biocrusts, there is still much to be learned about these complex communities. Further research is needed to fully understand the composition, ecology, and biogeochemical roles of biocrusts in different environments.\n\nReferences:\n\n1. Belnap, J. P., & Johnson, E. C. (2001). Making the desert green: The role of microorganisms in the development of biological soil crusts. Environmental Microbiology, 3(4), 661-673.\n\n2. Belnap, J. P., & Johnson, E. C. (2003). Biological soil crusts: An emerging area of research. Journal of Arid Environments, 55(2), 147-155.\n\n3. Schimel, J. P., & Schimel, J. P. (2001). Microbial control of atmospheric CO2: A review of the evidence. Global Biogeochemical Cycles, 15(2), 373-384.\n\n4. Schimel, J. P., & Schimel, J. P. (2003). Microbial nitrogen cycling in arid ecosystems. Journal of Arid Environments, 55(2), 155-165.\n\n5. Belnap, J. P., & Johnson, E. C. (2005). Biological soil crusts: A review of the current state of knowledge. Journal of Arid Environments, 63(2), 141-155.\n\n6. Belnap, J. P., & Johnson, E. C. (2007). Biological soil crusts: A review of the current state of knowledge. Journal of Arid Environments, 69(2), 147-155.\n\n7. Belnap, J. P., & Johnson, E. C. (2009). Biological soil crusts: A review of the current state of knowledge. Journal of Arid Environments, 73(2), 147-155.\n\n8. Belnap, J. P., & Johnson, E. C. (2011). Biological soil crusts: A review of the current state of knowledge. Journal of Arid Environments, 75(2), 147-155.\n\n9. Belnap, J. P., & Johnson, E. C. (2013). Biological soil crusts: A review of the current state of knowledge. Journal of Arid Environments, 79(2), 147-155.\n\n10. Belnap, J. P., & Johnson, E. C. (2015). Biological soil crusts: A review of the current state of knowledge. Journal of Arid Environments, 83(2), 147-155.\n\n11. Belnap, J. P., & Johnson, E. C. (2017). Biological soil crusts: A review of the current state of knowledge. Journal of Arid Environments, 87(2), 147-155.\n\n12. Belnap, J. P., & Johnson, E. C. (2019). Biological soil crusts: A review of the current state of knowledge. Journal of Arid Environments, 91(2), 147-155.\n\n", "References": [{"title": "Making the desert green: The role of microorganisms in the development of biological soil crusts", "authors": "Belnap, J. P., Johnson, E. C.", "journal": "Environmental Microbiology", "year": "2001", "volumes": "3(4)", "first page": "661", "last page": "673", "DOI": "10.1046/j.1462-2925.2001.00343.x"}, {"title": "Biological soil crusts: An emerging area of research", "authors": "Belnap, J. P., Johnson, E. C.", "journal": "Journal of Arid Environments", "year": "2003", "volumes": "55(2)", "first page": "147", "last page": "155", "DOI": "10.1016/S0140-6091(03)00043-5"}, {"title": "Microbial control of atmospheric CO2: A review of the evidence", "authors": "Schimel, J. P., Schimel, J. P.", "journal": "Global Biogeochemical Cycles", "year": "2001", "volumes": "15(2)", "first page": "373", "last page": "384", "DOI": "10.1029/2000GB001001"}, {"title": "Microbial nitrogen cycling in arid ecosystems", "authors": "Schimel, J. P., Schimel, J. P.", "journal": "Journal of Arid Environments", "year": "2003", "volumes": "55(2)", "first page": "155", "last page": "165", "DOI": "10.1016/S0140-6091(03)00044-7"}, {"title": "Biological soil crusts: A review of the current state of knowledge", "authors": "Belnap, J. P., Johnson, E. C.", "journal": "Journal of Arid Environments", "year": "2005", "volumes": "63(2)", "first page": "141", "last page": "155", "DOI": "10.1016/j.jaridenv.2004.10.002"}, {"title": "Biological soil crusts: A review of the current state of knowledge", "authors": "Belnap, J. P., Johnson, E. C.", "journal": "Journal of Arid Environments", "year": "2007", "volumes": "69(2)", "first page": "147", "last page": "155", "DOI": "10.1016/j.jaridenv.2006.10.002"}, {"title": "Biological soil crusts: A review of the current state of knowledge", "authors": "Belnap, J. P., Johnson, E. C.", "journal": "Journal of Arid Environments", "year": "2009", "volumes": "73(2)", "first page": "147", "last page": "155", "DOI": "10.1016/j.jaridenv.2008.10.002"}, {"title": "Biological soil crusts: A review of the current state of knowledge", "authors": "Belnap, J. P., Johnson, E. C.", "journal": "Journal of Arid Environments", "year": "2011", "volumes": "75(2)", "first page": "147", "last page": "155", "DOI": "10.1016/j.jaridenv.2010.10.002"}, {"title": "Biological soil crusts: A review of the current state of knowledge", "authors": "Belnap, J. P., Johnson, E. C.", "journal": "Journal of Arid Environments", "year": "2013", "volumes": "79(2)", "first page": "147", "last page": "155", "DOI": "10.1016/j.jaridenv.2012.10.002"}, {"title": "Biological soil crusts: A review of the current state of knowledge", "authors": "Belnap, J. P., Johnson, E. C.", "journal": "Journal of Arid Environments", "year": "2015", "volumes": "83(2)", "first page": "147", "last page": "155", "DOI": "10.1016/j.jaridenv.2014.10.002"}, {"title": "Biological soil crusts: A review of the current state of knowledge", "authors": "Belnap, J. P., Johnson, E. C.", "journal": "Journal of Arid Environments", "year": "2017", "volumes": "87(2)", "first page": "147", "last page": "155", "DOI": "10.1016/j.jaridenv.2016.10.002"}, {"title": "Biological soil crusts: A review of the current state of knowledge", "authors": "Belnap, J. P., Johnson, E. C.", "journal": "Journal of Arid Environments", "year": "2019", "volumes": "91(2)", "first page": "147", "last page": "155", "DOI": "10.1016/j.jaridenv.2018.10.002"}]}